tennetsac/__init__.py
tennetsac/core.py
tennetsac/ckpt_files/base.ckpt
tennetsac/ckpt_files/geo.ckpt
tennetsac/ckpt_files/prf.ckpt
tennetsac/ckpt_files/fine-tuned/1.ckpt
tennetsac/ckpt_files/fine-tuned/10.ckpt
tennetsac/ckpt_files/fine-tuned/2.ckpt
tennetsac/ckpt_files/fine-tuned/3.ckpt
tennetsac/ckpt_files/fine-tuned/4.ckpt
tennetsac/ckpt_files/fine-tuned/5.ckpt
tennetsac/ckpt_files/fine-tuned/6.ckpt
tennetsac/ckpt_files/fine-tuned/7.ckpt
tennetsac/ckpt_files/fine-tuned/8.ckpt
tennetsac/ckpt_files/fine-tuned/9.ckpt
tennetsac/models/Emb2Geometry.py
tennetsac/models/Emb2Profile.py
tennetsac/models/Prf2Gamma.py
tennetsac/utils/embedding.py
tennetsac/utils/model_io.py
tennetsac/utils/plotting.py
tennetsac/utils/property.py
tennetsac/utils/smiles.py
tennetsac/utils/smi_ted_light/bert_vocab_curated.txt
tennetsac/utils/smi_ted_light/load.py
tennetsac/utils/smi_ted_light/fast_transformers/__init__.py
tennetsac/utils/smi_ted_light/fast_transformers/masking.py
tennetsac/utils/smi_ted_light/fast_transformers/transformers.py
tennetsac/utils/smi_ted_light/fast_transformers/utils.py
tennetsac/utils/smi_ted_light/fast_transformers/weight_mapper.py
tennetsac/utils/smi_ted_light/fast_transformers/aggregate/__init__.py
tennetsac/utils/smi_ted_light/fast_transformers/attention/__init__.py
tennetsac/utils/smi_ted_light/fast_transformers/attention/attention_layer.py
tennetsac/utils/smi_ted_light/fast_transformers/attention/causal_linear_attention.py
tennetsac/utils/smi_ted_light/fast_transformers/attention/clustered_attention.py
tennetsac/utils/smi_ted_light/fast_transformers/attention/conditional_full_attention.py
tennetsac/utils/smi_ted_light/fast_transformers/attention/exact_topk_attention.py
tennetsac/utils/smi_ted_light/fast_transformers/attention/full_attention.py
tennetsac/utils/smi_ted_light/fast_transformers/attention/improved_clustered_attention.py
tennetsac/utils/smi_ted_light/fast_transformers/attention/improved_clustered_causal_attention.py
tennetsac-0.1.10.dist-info/METADATA
tennetsac-0.1.10.dist-info/WHEEL
tennetsac-0.1.10.dist-info/top_level.txt
tennetsac-0.1.10.dist-info/RECORD
