Metadata-Version: 2.4
Name: tennetsac
Version: 0.1.10
Summary: Thermodynamics-embedded Neural Network for Segment Activity Coefficients
Author: Yue Yang
License: MIT
Requires-Python: <3.13,>=3.9
Requires-Dist: numpy<2,>=1.25
Requires-Dist: pandas<2.2
Requires-Dist: pyarrow<15
Requires-Dist: scikit-learn
Requires-Dist: scipy
Requires-Dist: rdkit
Requires-Dist: tqdm
Requires-Dist: transformers==4.36.2
Requires-Dist: safetensors
Requires-Dist: tokenizers
Requires-Dist: accelerate
Requires-Dist: torch>=2.1.2
Requires-Dist: torchvision>=0.16
Requires-Dist: torchaudio>=2.1
Provides-Extra: dev
Requires-Dist: jupyterlab; extra == "dev"
